setup.py
calbmi_lungsang/__init__.py
calbmi_lungsang/bmi_calculate_lungs.py
calbmi_lungsang.egg-info/PKG-INFO
calbmi_lungsang.egg-info/SOURCES.txt
calbmi_lungsang.egg-info/dependency_links.txt
calbmi_lungsang.egg-info/not-zip-safe
calbmi_lungsang.egg-info/top_level.txt