Metadata-Version: 2.1
Name: calbmi-lungsang
Version: 0.1
Summary: Calculate Body-Mass Indes
Author: Lungsang
